fba_finance/__init__.py
fba_finance/aggregator.py
fba_finance/client.py
fba_finance/config.py
fba_finance/market_hours.py
fba_finance/models.py
fba_finance/portfolio.py
fba_finance/screener.py
fba_finance/usage_tracker.py
fba_finance/core/__init__.py
fba_finance/core/cache.py
fba_finance/core/rate_limiter-fbandini.py
fba_finance/core/rate_limiter.py
fba_finance/providers/__init__.py
fba_finance/providers/alphavantage_extensions.py
fba_finance/providers/alphavantage_provider.py
fba_finance/providers/base.py
fba_finance/providers/twelvedata_extensions.py
fba_finance/providers/twelvedata_provider.py
fba_finance/providers/yahoo_scraper.py
fba_finance/providers/yahooquery_extensions.py
fba_finance/providers/yahooquery_provider.py
fba_finance/providers/yfinance_extensions.py
fba_finance/providers/yfinance_provider.py
fba_finance/yfinance_compat/__init__.py
fba_finance/yfinance_compat/download.py
fba_finance/yfinance_compat/ticker.py
fba_finance-0.2.2.dist-info/LICENSE
fba_finance-0.2.2.dist-info/METADATA
fba_finance-0.2.2.dist-info/WHEEL
fba_finance-0.2.2.dist-info/top_level.txt
fba_finance-0.2.2.dist-info/RECORD
