Metadata-Version: 2.1
Name: fba-finance
Version: 0.2.2
Summary: Multi-source financial data library with anti-rate-limiting strategies
Home-page: https://github.com/faux62/fba_finance
Author: Fausto Bandini
License: UNKNOWN
Platform: UNKNOWN
Classifier: Development Status :: 3 - Alpha
Classifier: Intended Audience :: Developers
Classifier: Intended Audience :: Financial and Insurance Industry
Classifier: Topic :: Office/Business :: Financial :: Investment
Classifier: License :: OSI Approved :: MIT License
Classifier: Programming Language :: Python :: 3
Classifier: Programming Language :: Python :: 3.8
Classifier: Programming Language :: Python :: 3.9
Classifier: Programming Language :: Python :: 3.10
Classifier: Programming Language :: Python :: 3.11
Requires-Python: >=3.8
License-File: LICENSE
Requires-Dist: requests>=2.31.0
Requires-Dist: pandas>=2.0.0
Requires-Dist: numpy>=1.24.0
Requires-Dist: yfinance>=0.2.32
Requires-Dist: yahooquery>=2.3.0
Requires-Dist: beautifulsoup4>=4.12.0
Requires-Dist: lxml>=4.9.0
Requires-Dist: ratelimit>=2.2.1
Requires-Dist: diskcache>=5.6.3
Requires-Dist: aiohttp>=3.9.0
Requires-Dist: python-dotenv>=1.0.0
Requires-Dist: fake-useragent>=1.4.0
Provides-Extra: full
Requires-Dist: alpha-vantage>=2.3.1; extra == "full"
Requires-Dist: twelvedata>=1.2.14; extra == "full"
Requires-Dist: selenium>=4.15.0; extra == "full"
Requires-Dist: playwright>=1.40.0; extra == "full"
Requires-Dist: redis>=5.0.0; extra == "full"
Requires-Dist: websockets>=12.0; extra == "full"
